ezpyide/__init__.py
ezpyide/__main__.py
ezpyide/app.py
ezpyide-1.0.1.dist-info/METADATA
ezpyide-1.0.1.dist-info/WHEEL
ezpyide-1.0.1.dist-info/entry_points.txt
ezpyide-1.0.1.dist-info/top_level.txt
ezpyide-1.0.1.dist-info/RECORD
