Metadata-Version: 2.4
Name: ezpyide
Version: 1.0.1
Summary: Web IDE for Python using Streamlit and Ace Editor
Home-page: https://github.com/DenisVargaeu/ezpyide
Author: Denis Varga
Requires-Dist: streamlit>=1.0.0
Requires-Dist: streamlit_ace>=0.1.0
Dynamic: author
Dynamic: description
Dynamic: description-content-type
Dynamic: home-page
Dynamic: requires-dist
Dynamic: summary
